{
	"users": [
	  {
		"id": 1,
		"username": "admin",
		"password": "admin123"
	  }
	],
	"tables": [
	  {
		"id": 1,
		"name": "Bàn 1",
		"capacity": 4,
		"isOccupied": false
	  },
	  {
		"id": 2,
		"name": "Bàn 2",
		"capacity": 2,
		"isOccupied": true
	  }
	],
	"food": [
	{
	"id": 1,
	"name": "Mì cay hải sản",
	"price": 20000,
	"description": "Mì cay hải sản, với nước dùng đậm đà và các loại hải sản tươi ngon.",
	"image": "https://www.flaticon.com/free-icon/ramen_2276941?term=noodle&page=1&position=6&origin=search&related_id=2276941"
	},
	{
	"id": 2,
	"name": "Mì cay bò Mỹ",
	"price": 10000,
	"description": "Mì cay bò Mỹ với thịt bò tươi ngon, sốt cay đặc trưng và gia vị thơm ngon.",
	"image": "https://www.flaticon.com/free-icon/ramen_2276941?term=noodle&page=1&position=6&origin=search&related_id=2276941"
	},
	{
	"id": 3,
	"name": "Mỳ cay bò Úc",
	"price": 10000,
	"description": "Mỳ cay bò Úc, được chế biến với thịt bò Úc mềm, gia vị đặc biệt và nước dùng cay nồng.",
	"image": "https://www.flaticon.com/free-icon/ramen_2276941?term=noodle&page=1&position=6&origin=search&related_id=2276941"
	},
	{
	"id": 4,
	"name": "Mỳ cay thập cẩm",
	"price": 10000,
	"description": "Mỳ cay thập cẩm, kết hợp nhiều loại nguyên liệu như thịt, hải sản và rau củ tươi ngon.",
	"image": "https://www.flaticon.com/free-icon/ramen_2276941?term=noodle&page=1&position=6&origin=search&related_id=2276941"
	},
	{
	"id": 5,
	"name": "Mì cay Hàn Quốc",
	"price": 10000,
	"description": "Mì cay Hàn Quốc, món mì truyền thống với nước dùng cay và các gia vị đặc trưng của Hàn Quốc.",
	"image": "https://www.flaticon.com/free-icon/ramen_2276941?term=noodle&page=1&position=6&origin=search&related_id=2276941"
	}
	],
	"orders": [
	  {
		"id": 1,
		"tableId": 1,
		"items": [
		  {"name": "Bánh mì", "quantity": 2, "price": 20000, "image": "https://example.com/images/banhmi.jpg"},
		  {"name": "Coca-Cola", "quantity": 1, "price": 10000, "image": "https://example.com/images/coca.jpg"}
		],
		"totalAmount": 50000,
		"orderDate": "2024-12-29T10:00:00"
	  }
	]
  }
  